{"coord":{"lon":-73.8,"lat":40.7},"weather":[{"id":211,"main":"Thunderstorm","description":"proximity thunderstorm","icon":"11n"},{"id":501,"main":"Rain","description":"moderate rain","icon":"10n"},{"id":701,"main":"Mist","description":"mist","icon":"50n"}],"base":"stations","main":{"temp":284.52,"pressure":1015,"humidity":81,"temp_min":281.15,"temp_max":286.15},"visibility":16093,"wind":{"speed":2.1,"deg":50},"clouds":{"all":90},"dt":1447299960,"sys":{"type":1,"id":2120,"message":0.0456,"country":"US","sunrise":1447328299,"sunset":1447364392},"id":5133268,"name":"Queens County","cod":200}
